django_autoconfig/__init__.py
django_autoconfig/app_settings.py
django_autoconfig/autoconfig.py
django_autoconfig/autourlconf.py
django_autoconfig/models.py
django_autoconfig/version.py
django_autoconfig/contrib/__init__.py
django_autoconfig/contrib/admin/__init__.py
django_autoconfig/contrib/admin/urls.py
django_autoconfig/environment_settings/__init__.py
django_autoconfig/environment_settings/autoconfig.py
django_autoconfig/tests/__init__.py
django_autoconfig/tests/index_view_urlconf.py
django_autoconfig/tests/test_autoconfig.py
django_autoconfig/tests/app1/__init__.py
django_autoconfig/tests/app2/__init__.py
django_autoconfig/tests/app3/__init__.py
django_autoconfig/tests/app_18templates1/__init__.py
django_autoconfig/tests/app_18templates1/autoconfig.py
django_autoconfig/tests/app_18templates2/__init__.py
django_autoconfig/tests/app_18templates2/autoconfig.py
django_autoconfig/tests/app_blank_autoconfig/__init__.py
django_autoconfig/tests/app_blank_autoconfig/autoconfig.py
django_autoconfig/tests/app_blank_urls/__init__.py
django_autoconfig/tests/app_blank_urls/urls.py
django_autoconfig/tests/app_boolean/__init__.py
django_autoconfig/tests/app_boolean/autoconfig.py
django_autoconfig/tests/app_boolean_inconsistent/__init__.py
django_autoconfig/tests/app_boolean_inconsistent/autoconfig.py
django_autoconfig/tests/app_broken_autoconfig/__init__.py
django_autoconfig/tests/app_broken_autoconfig/autoconfig.py
django_autoconfig/tests/app_broken_urls/__init__.py
django_autoconfig/tests/app_broken_urls/urls.py
django_autoconfig/tests/app_contrib_admin/__init__.py
django_autoconfig/tests/app_contrib_admin/autoconfig.py
django_autoconfig/tests/app_default_settings/__init__.py
django_autoconfig/tests/app_default_settings/autoconfig.py
django_autoconfig/tests/app_list/__init__.py
django_autoconfig/tests/app_list/autoconfig.py
django_autoconfig/tests/app_middleware/__init__.py
django_autoconfig/tests/app_middleware/autoconfig.py
django_autoconfig-0.8.0.dist-info/METADATA
django_autoconfig-0.8.0.dist-info/RECORD
django_autoconfig-0.8.0.dist-info/WHEEL
django_autoconfig-0.8.0.dist-info/top_level.txt
